{
  "part_id": "m0166-05-0001-00",
  "metadata": {},
  "dimensions": [
    {
      "type": "DIMENSION",
      "dimension_type": null,
      "text": "28",
      "measured": null,
      "pos": [
        131.9992165024,
        113.7218994646
      ],
      "layer": "M0166-05-0001-00_DXF_DIMENSION",
      "handle": "AE6",
      "Z": false,
      "text_ai": "28",
      "text_ai_source": "28"
    },
    {
      "type": "DIMENSION",
      "dimension_type": null,
      "text": "0",
      "measured": null,
      "pos": [
        214.8869250755,
        261.3414026459
      ],
      "layer": "M0166-05-0001-00_DXF_DIMENSION",
      "handle": "AE7",
      "Z": false,
      "text_ai": "0",
      "text_ai_source": "0"
    },
    {
      "type": "DIMENSION",
      "dimension_type": null,
      "text": "72.0.5",
      "measured": null,
      "pos": [
        253.9841459667,
        154.5596024525
      ],
      "layer": "M0166-05-0001-00_DXF_DIMENSION",
      "handle": "AE8",
      "Z": false,
      "text_ai": "72.0.5",
      "text_ai_source": "72.0.5"
    },
    {
      "type": "DIMENSION",
      "dimension_type": null,
      "text": "M0166-05-0001-00",
      "measured": null,
      "pos": [
        157.7526338486,
        184.4488140963
      ],
      "layer": "M0166-05-0001-00_DXF_DIMENSION",
      "handle": "AF9",
      "Z": false,
      "text_ai": "M0166-05-0001-00",
      "text_ai_source": "M0166-05-0001-00"
    },
    {
      "type": "DIMENSION",
      "dimension_type": null,
      "text": "FLANGE MODEL TARGET",
      "measured": null,
      "pos": [
        151.2107776952,
        216.1362889902
      ],
      "layer": "M0166-05-0001-00_DXF_DIMENSION",
      "handle": "B0A",
      "Z": false,
      "text_ai": "SIZE\nA3",
      "text_ai_source": "SCALE\nDESIGNATION\nSIZE\nA3"
    },
    {
      "type": "DIMENSION",
      "dimension_type": null,
      "text": "48",
      "measured": null,
      "pos": [
        202.8869250755,
        242.8839597094
      ],
      "layer": "M0166-05-0001-00_DXF_DIMENSION",
      "handle": "B0B",
      "Z": false,
      "text_ai": "48",
      "text_ai_source": "48"
    },
    {
      "type": "DIMENSION",
      "dimension_type": null,
      "text": "48",
      "measured": null,
      "pos": [
        233.7122630292,
        214.5596024525
      ],
      "layer": "M0166-05-0001-00_DXF_DIMENSION",
      "handle": "B0C",
      "Z": false,
      "text_ai": "48",
      "text_ai_source": "48"
    },
    {
      "type": "DIMENSION",
      "dimension_type": null,
      "text": "4x R6",
      "measured": null,
      "pos": [
        148.8869250755,
        160.5596024525
      ],
      "layer": "M0166-05-0001-00_DXF_DIMENSION",
      "handle": "B0D",
      "Z": false,
      "text_ai": "4 x R6",
      "text_ai_source": "4x R6"
    }
  ],
  "datums": [
    {
      "datum": "A",
      "pos": [
        103.9954099417,
        175.7290180525
      ],
      "source": "text"
    },
    {
      "datum": "B",
      "pos": [
        110.1954099417,
        175.7290180525
      ],
      "source": "text"
    },
    {
      "datum": "C",
      "pos": [
        123.7287432751,
        175.7290180525
      ],
      "source": "text"
    },
    {
      "datum": "A",
      "pos": [
        101.4925753982,
        222.371759334
      ],
      "source": "text"
    },
    {
      "datum": "B",
      "pos": [
        107.6925753982,
        222.371759334
      ],
      "source": "text"
    },
    {
      "datum": "C",
      "pos": [
        121.2259087316,
        222.371759334
      ],
      "source": "text"
    },
    {
      "datum": "B",
      "pos": [
        119.449666168,
        259.1796033372
      ],
      "source": "text"
    },
    {
      "datum": "C",
      "pos": [
        165.4509428042,
        138.277727902
      ],
      "source": "text"
    },
    {
      "datum": "A",
      "pos": [
        226.3662384726,
        99.9512301788
      ],
      "source": "text"
    },
    {
      "datum": "R",
      "pos": [
        129.0847389454,
        145.4074163225
      ],
      "source": "block:*D7"
    }
  ],
  "arrows": [
    {
      "type": "LWPOLYLINE",
      "points": [
        [
          71.0287445068,
          177.7290161133
        ],
        [
          71.1954089355,
          177.0623455811
        ],
        [
          71.3620797729,
          176.7290167236
        ],
        [
          71.6954086304,
          176.2290234375
        ],
        [
          72.3620791626,
          175.8956817627
        ],
        [
          73.0287432861,
          175.729017334
        ],
        [
          73.6954074097,
          175.8956817627
        ],
        [
          74.0287426758,
          176.0623461914
        ],
        [
          74.5287423706,
          176.3956878662
        ],
        [
          74.8620776367,
          177.0623455811
        ],
        [
          75.0287420654,
          177.7290161133
        ],
        [
          74.8620776367,
          178.3956866455
        ],
        [
          74.6954067993,
          178.7290155029
        ],
        [
          74.3620779419,
          179.2290216064
        ],
        [
          73.6954074097,
          179.5623504639
        ],
        [
          73.0287432861,
          179.7290148926
        ],
        [
          72.3620791626,
          179.5623504639
        ],
        [
          72.0287438965,
          179.3956860352
        ],
        [
          71.5287442017,
          179.0623571777
        ],
        [
          71.1954089355,
          178.3956866455
        ],
        [
          71.0287445068,
          177.7290161133
        ]
      ],
      "layer": "M0166-05-0001-00_DXF_DIMENSION",
      "handle": "AE9"
    },
    {
      "type": "LINE",
      "start": [
        70.0287451172,
        177.7290161133
      ],
      "end": [
        76.0287414551,
        177.7290161133
      ],
      "layer": "M0166-05-0001-00_DXF_DIMENSION",
      "handle": "AEA"
    },
    {
      "type": "LINE",
      "start": [
        73.0287432861,
        174.7290179443
      ],
      "end": [
        73.0287432861,
        180.7290142822
      ],
      "layer": "M0166-05-0001-00_DXF_DIMENSION",
      "handle": "AEB"
    },
    {
      "type": "LWPOLYLINE",
      "points": [
        [
          93.1620767212,
          177.7290161133
        ],
        [
          93.3287411499,
          176.8956811523
        ],
        [
          93.4954119873,
          176.3956878662
        ],
        [
          93.8287408447,
          175.8956817627
        ],
        [
          94.3287405396,
          175.3956884766
        ],
        [
          94.8287402344,
          175.0623468018
        ],
        [
          95.3287463379,
          174.895682373
        ],
        [
          96.1620748901,
          174.7290179443
        ],
        [
          96.9954098511,
          174.895682373
        ],
        [
          97.4954095459,
          175.0623468018
        ],
        [
          97.9954092407,
          175.3956884766
        ],
        [
          98.4954089355,
          175.8956817627
        ],
        [
          98.8287442017,
          176.3956878662
        ],
        [
          98.9954086304,
          176.8956811523
        ],
        [
          99.1620794678,
          177.7290161133
        ],
        [
          98.9954086304,
          178.5623510742
        ],
        [
          98.8287442017,
          179.0623571777
        ],
        [
          98.4954089355,
          179.5623504639
        ],
        [
          97.9954092407,
          180.0623565674
        ],
        [
          97.4954095459,
          180.3956854248
        ],
        [
          96.9954098511,
          180.5623498535
        ],
        [
          96.1620748901,
          180.7290142822
        ],
        [
          95.3287463379,
          180.5623498535
        ],
        [
          94.8287402344,
          180.3956854248
        ],
        [
          94.3287405396,
          180.0623565674
        ],
        [
          93.8287408447,
          179.5623504639
        ],
        [
          93.4954119873,
          179.0623571777
        ],
        [
          93.3287411499,
          178.5623510742
        ],
        [
          93.1620767212,
          177.7290161133
        ]
      ],
      "layer": "M0166-05-0001-00_DXF_DIMENSION",
      "handle": "AEC"
    },
    {
      "type": "LWPOLYLINE",
      "points": [
        [
          94.495411377,
          176.0623461914
        ],
        [
          94.495411377,
          179.3956860352
        ],
        [
          96.1620748901,
          176.0623461914
        ],
        [
          97.828744812,
          179.3956860352
        ],
        [
          97.828744812,
          176.0623461914
        ]
      ],
      "layer": "M0166-05-0001-00_DXF_DIMENSION",
      "handle": "AED"
    },
    {
      "type": "LWPOLYLINE",
      "points": [
        [
          113.395411377,
          177.7290161133
        ],
        [
          113.5620758057,
          176.8956811523
        ],
        [
          113.7287402344,
          176.3956878662
        ],
        [
          114.0620819092,
          175.8956817627
        ],
        [
          114.5620751953,
          175.3956884766
        ],
        [
          115.0620812988,
          175.0623468018
        ],
        [
          115.562074585,
          174.895682373
        ],
        [
          116.3954095459,
          174.7290179443
        ],
        [
          117.2287445068,
          174.895682373
        ],
        [
          117.728737793,
          175.0623468018
        ],
        [
          118.2287438965,
          175.3956884766
        ],
        [
          118.7287371826,
          175.8956817627
        ],
        [
          119.0620788574,
          176.3956878662
        ],
        [
          119.2287432861,
          176.8956811523
        ],
        [
          119.3954077148,
          177.7290161133
        ],
        [
          119.2287432861,
          178.5623510742
        ],
        [
          119.0620788574,
          179.0623571777
        ],
        [
          118.7287371826,
          179.5623504639
        ],
        [
          118.2287438965,
          180.0623565674
        ],
        [
          117.728737793,
          180.3956854248
        ],
        [
          117.2287445068,
          180.5623498535
        ],
        [
          116.3954095459,
          180.7290142822
        ],
        [
          115.562074585,
          180.5623498535
        ],
        [
          115.0620812988,
          180.3956854248
        ],
        [
          114.5620751953,
          180.0623565674
        ],
        [
          114.0620819092,
          179.5623504639
        ],
        [
          113.7287402344,
          179.0623571777
        ],
        [
          113.5620758057,
          178.5623510742
        ],
        [
          113.395411377,
          177.7290161133
        ]
      ],
      "layer": "M0166-05-0001-00_DXF_DIMENSION",
      "handle": "AF0"
    },
    {
      "type": "LWPOLYLINE",
      "points": [
        [
          114.728739624,
          176.0623461914
        ],
        [
          114.728739624,
          179.3956860352
        ],
        [
          116.3954095459,
          176.0623461914
        ],
        [
          118.0620794678,
          179.3956860352
        ],
        [
          118.0620794678,
          176.0623461914
        ]
      ],
      "layer": "M0166-05-0001-00_DXF_DIMENSION",
      "handle": "AF1"
    },
    {
      "type": "LWPOLYLINE",
      "points": [
        [
          126.9287475586,
          177.7290161133
        ],
        [
          127.0954119873,
          176.8956811523
        ],
        [
          127.262076416,
          176.3956878662
        ],
        [
          127.5954052734,
          175.8956817627
        ],
        [
          128.095411377,
          175.3956884766
        ],
        [
          128.5954046631,
          175.0623468018
        ],
        [
          129.0954107666,
          174.895682373
        ],
        [
          129.9287457275,
          174.7290179443
        ],
        [
          130.7620806885,
          174.895682373
        ],
        [
          131.2620739746,
          175.0623468018
        ],
        [
          131.7620800781,
          175.3956884766
        ],
        [
          132.2620733643,
          175.8956817627
        ],
        [
          132.5954150391,
          176.3956878662
        ],
        [
          132.7620794678,
          176.8956811523
        ],
        [
          132.9287438965,
          177.7290161133
        ],
        [
          132.7620794678,
          178.5623510742
        ],
        [
          132.5954150391,
          179.0623571777
        ],
        [
          132.2620733643,
          179.5623504639
        ],
        [
          131.7620800781,
          180.0623565674
        ],
        [
          131.2620739746,
          180.3956854248
        ],
        [
          130.7620806885,
          180.5623498535
        ],
        [
          129.9287457275,
          180.7290142822
        ],
        [
          129.0954107666,
          180.5623498535
        ],
        [
          128.5954046631,
          180.3956854248
        ],
        [
          128.095411377,
          180.0623565674
        ],
        [
          127.5954052734,
          179.5623504639
        ],
        [
          127.262076416,
          179.0623571777
        ],
        [
          127.0954119873,
          178.5623510742
        ],
        [
          126.9287475586,
          177.7290161133
        ]
      ],
      "layer": "M0166-05-0001-00_DXF_DIMENSION",
      "handle": "AF2"
    },
    {
      "type": "LWPOLYLINE",
      "points": [
        [
          128.2620758057,
          176.0623461914
        ],
        [
          128.2620758057,
          179.3956860352
        ],
        [
          129.9287457275,
          176.0623461914
        ],
        [
          131.5954156494,
          179.3956860352
        ],
        [
          131.5954156494,
          176.0623461914
        ]
      ],
      "layer": "M0166-05-0001-00_DXF_DIMENSION",
      "handle": "AF3"
    },
    {
      "type": "LWPOLYLINE",
      "points": [
        [
          68.5259069824,
          224.3717541504
        ],
        [
          68.6925778198,
          223.7050964355
        ],
        [
          68.8592422485,
          223.3717675781
        ],
        [
          69.1925775146,
          222.8717614746
        ],
        [
          69.8592416382,
          222.5384326172
        ],
        [
          70.5259057617,
          222.3717553711
        ],
        [
          71.1925762939,
          222.5384326172
        ],
        [
          71.5259115601,
          222.7050842285
        ],
        [
          72.0259112549,
          223.0384387207
        ],
        [
          72.3592401123,
          223.7050964355
        ],
        [
          72.5259109497,
          224.3717541504
        ],
        [
          72.3592401123,
          225.0384375
        ],
        [
          72.1925756836,
          225.3717663574
        ],
        [
          71.8592404175,
          225.8717468262
        ],
        [
          71.1925762939,
          226.2051013184
        ],
        [
          70.5259057617,
          226.3717529297
        ],
        [
          69.8592416382,
          226.2051013184
        ],
        [
          69.5259063721,
          226.0384240723
        ],
        [
          69.0259066772,
          225.7050952148
        ],
        [
          68.6925778198,
          225.0384375
        ],
        [
          68.5259069824,
          224.3717541504
        ]
      ],
      "layer": "M0166-05-0001-00_DXF_DIMENSION",
      "handle": "AFA"
    },
    {
      "type": "LINE",
      "start": [
        67.5259075928,
        224.3717541504
      ],
      "end": [
        73.5259103394,
        224.3717541504
      ],
      "layer": "M0166-05-0001-00_DXF_DIMENSION",
      "handle": "AFB"
    },
    {
      "type": "LINE",
      "start": [
        70.5259057617,
        221.3717687988
      ],
      "end": [
        70.5259057617,
        227.3717651367
      ],
      "layer": "M0166-05-0001-00_DXF_DIMENSION",
      "handle": "AFC"
    },
    {
      "type": "LWPOLYLINE",
      "points": [
        [
          90.6592391968,
          224.3717541504
        ],
        [
          90.8259100342,
          223.5384191895
        ],
        [
          90.9925744629,
          223.0384387207
        ],
        [
          91.325909729,
          222.5384326172
        ],
        [
          91.8259094238,
          222.0384265137
        ],
        [
          92.3259091187,
          221.7050976562
        ],
        [
          92.8259088135,
          221.5384204102
        ],
        [
          93.6592437744,
          221.3717687988
        ],
        [
          94.4925723267,
          221.5384204102
        ],
        [
          94.9925784302,
          221.7050976562
        ],
        [
          95.492578125,
          222.0384265137
        ],
        [
          95.9925778198,
          222.5384326172
        ],
        [
          96.3259066772,
          223.0384387207
        ],
        [
          96.4925775146,
          223.5384191895
        ],
        [
          96.6592419434,
          224.3717541504
        ],
        [
          96.4925775146,
          225.2050891113
        ],
        [
          96.3259066772,
          225.7050952148
        ],
        [
          95.9925778198,
          226.2051013184
        ],
        [
          95.492578125,
          226.7050817871
        ],
        [
          94.9925784302,
          227.0384362793
        ],
        [
          94.4925723267,
          227.2050878906
        ],
        [
          93.6592437744,
          227.3717651367
        ],
        [
          92.8259088135,
          227.2050878906
        ],
        [
          92.3259091187,
          227.0384362793
        ],
        [
          91.8259094238,
          226.7050817871
        ],
        [
          91.325909729,
          226.2051013184
        ],
        [
          90.9925744629,
          225.7050952148
        ],
        [
          90.8259100342,
          225.2050891113
        ],
        [
          90.6592391968,
          224.3717541504
        ]
      ],
      "layer": "M0166-05-0001-00_DXF_DIMENSION",
      "handle": "AFD"
    },
    {
      "type": "LWPOLYLINE",
      "points": [
        [
          91.9925738525,
          222.7050842285
        ],
        [
          91.9925738525,
          226.0384240723
        ],
        [
          93.6592437744,
          222.7050842285
        ],
        [
          95.3259072876,
          226.0384240723
        ],
        [
          95.3259072876,
          222.7050842285
        ]
      ],
      "layer": "M0166-05-0001-00_DXF_DIMENSION",
      "handle": "AFE"
    },
    {
      "type": "LWPOLYLINE",
      "points": [
        [
          110.8925738525,
          224.3717541504
        ],
        [
          111.0592382812,
          223.5384191895
        ],
        [
          111.22590271,
          223.0384387207
        ],
        [
          111.5592443848,
          222.5384326172
        ],
        [
          112.0592376709,
          222.0384265137
        ],
        [
          112.5592437744,
          221.7050976562
        ],
        [
          113.0592370605,
          221.5384204102
        ],
        [
          113.8925720215,
          221.3717687988
        ],
        [
          114.7259069824,
          221.5384204102
        ],
        [
          115.2259130859,
          221.7050976562
        ],
        [
          115.7259063721,
          222.0384265137
        ],
        [
          116.2259124756,
          222.5384326172
        ],
        [
          116.559241333,
          223.0384387207
        ],
        [
          116.7259057617,
          223.5384191895
        ],
        [
          116.8925701904,
          224.3717541504
        ],
        [
          116.7259057617,
          225.2050891113
        ],
        [
          116.559241333,
          225.7050952148
        ],
        [
          116.2259124756,
          226.2051013184
        ],
        [
          115.7259063721,
          226.7050817871
        ],
        [
          115.2259130859,
          227.0384362793
        ],
        [
          114.7259069824,
          227.2050878906
        ],
        [
          113.8925720215,
          227.3717651367
        ],
        [
          113.0592370605,
          227.2050878906
        ],
        [
          112.5592437744,
          227.0384362793
        ],
        [
          112.0592376709,
          226.7050817871
        ],
        [
          111.5592443848,
          226.2051013184
        ],
        [
          111.22590271,
          225.7050952148
        ],
        [
          111.0592382812,
          225.2050891113
        ],
        [
          110.8925738525,
          224.3717541504
        ]
      ],
      "layer": "M0166-05-0001-00_DXF_DIMENSION",
      "handle": "B01"
    },
    {
      "type": "LWPOLYLINE",
      "points": [
        [
          112.225914917,
          222.7050842285
        ],
        [
          112.225914917,
          226.0384240723
        ],
        [
          113.8925720215,
          222.7050842285
        ],
        [
          115.5592419434,
          226.0384240723
        ],
        [
          115.5592419434,
          222.7050842285
        ]
      ],
      "layer": "M0166-05-0001-00_DXF_DIMENSION",
      "handle": "B02"
    },
    {
      "type": "LWPOLYLINE",
      "points": [
        [
          124.4259100342,
          224.3717541504
        ],
        [
          124.5925744629,
          223.5384191895
        ],
        [
          124.7592388916,
          223.0384387207
        ],
        [
          125.0925805664,
          222.5384326172
        ],
        [
          125.5925738525,
          222.0384265137
        ],
        [
          126.0925799561,
          221.7050976562
        ],
        [
          126.5925732422,
          221.5384204102
        ],
        [
          127.4259082031,
          221.3717687988
        ],
        [
          128.2592431641,
          221.5384204102
        ],
        [
          128.7592364502,
          221.7050976562
        ],
        [
          129.2592425537,
          222.0384265137
        ],
        [
          129.7592358398,
          222.5384326172
        ],
        [
          130.0925775146,
          223.0384387207
        ],
        [
          130.2592419434,
          223.5384191895
        ],
        [
          130.4259063721,
          224.3717541504
        ],
        [
          130.2592419434,
          225.2050891113
        ],
        [
          130.0925775146,
          225.7050952148
        ],
        [
          129.7592358398,
          226.2051013184
        ],
        [
          129.2592425537,
          226.7050817871
        ],
        [
          128.7592364502,
          227.0384362793
        ],
        [
          128.2592431641,
          227.2050878906
        ],
        [
          127.4259082031,
          227.3717651367
        ],
        [
          126.5925732422,
          227.2050878906
        ],
        [
          126.0925799561,
          227.0384362793
        ],
        [
          125.5925738525,
          226.7050817871
        ],
        [
          125.0925805664,
          226.2051013184
        ],
        [
          124.7592388916,
          225.7050952148
        ],
        [
          124.5925744629,
          225.2050891113
        ],
        [
          124.4259100342,
          224.3717541504
        ]
      ],
      "layer": "M0166-05-0001-00_DXF_DIMENSION",
      "handle": "B03"
    },
    {
      "type": "LWPOLYLINE",
      "points": [
        [
          125.7592382812,
          222.7050842285
        ],
        [
          125.7592382812,
          226.0384240723
        ],
        [
          127.4259082031,
          222.7050842285
        ],
        [
          129.092578125,
          226.0384240723
        ],
        [
          129.092578125,
          222.7050842285
        ]
      ],
      "layer": "M0166-05-0001-00_DXF_DIMENSION",
      "handle": "B04"
    },
    {
      "type": "LINE",
      "start": [
        0.0,
        0.0
      ],
      "end": [
        0.0,
        297.0
      ],
      "layer": "M0166-05-0001-00_DXF_FORMAT",
      "handle": "B16"
    },
    {
      "type": "LINE",
      "start": [
        3.3952509012,
        297.0000002775
      ],
      "end": [
        3.405905876,
        0.1779492052
      ],
      "layer": "M0166-05-0001-00_DXF_FORMAT",
      "handle": "B17"
    },
    {
      "type": "LINE",
      "start": [
        14.8356380155,
        282.5542551285
      ],
      "end": [
        14.8354245646,
        289.1694801489
      ],
      "layer": "M0166-05-0001-00_DXF_FORMAT",
      "handle": "B18"
    },
    {
      "type": "LINE",
      "start": [
        25.2717610039,
        289.196255778
      ],
      "end": [
        25.274477862,
        285.8778110238
      ],
      "layer": "M0166-05-0001-00_DXF_FORMAT",
      "handle": "B19"
    },
    {
      "type": "LINE",
      "start": [
        25.274477862,
        285.8778110238
      ],
      "end": [
        25.2745845875,
        282.5701985136
      ],
      "layer": "M0166-05-0001-00_DXF_FORMAT",
      "handle": "B1A"
    },
    {
      "type": "LINE",
      "start": [
        30.1680430012,
        297.0
      ],
      "end": [
        30.1680430012,
        293.8171008285
      ],
      "layer": "M0166-05-0001-00_DXF_FORMAT",
      "handle": "B1B"
    },
    {
      "type": "LINE",
      "start": [
        40.5644084461,
        293.8162106875
      ],
      "end": [
        40.5647705634,
        282.5935511881
      ],
      "layer": "M0166-05-0001-00_DXF_FORMAT",
      "handle": "B1C"
    },
    {
      "type": "LINE",
      "start": [
        60.2100034785,
        297.0
      ],
      "end": [
        60.2100034785,
        293.8171008285
      ],
      "layer": "M0166-05-0001-00_DXF_FORMAT",
      "handle": "B1D"
    },
    {
      "type": "LINE",
      "start": [
        0.0,
        0.0
      ],
      "end": [
        420.0,
        0.0
      ],
      "layer": "M0166-05-0001-00_DXF_FORMAT",
      "handle": "B1E"
    },
    {
      "type": "LINE",
      "start": [
        370.4685201739,
        27.5206114677
      ],
      "end": [
        360.025003522,
        26.0221938612
      ],
      "layer": "M0166-05-0001-00_DXF_FORMAT",
      "handle": "B1F"
    },
    {
      "type": "LINE",
      "start": [
        272.1654197157,
        7.3340629561
      ],
      "end": [
        417.2308135105,
        7.875351739
      ],
      "layer": "M0166-05-0001-00_DXF_FORMAT",
      "handle": "B20"
    },
    {
      "type": "LINE",
      "start": [
        272.2798819558,
        10.7537381025
      ],
      "end": [
        417.2578995941,
        10.933388682
      ],
      "layer": "M0166-05-0001-00_DXF_FORMAT",
      "handle": "B21"
    },
    {
      "type": "LINE",
      "start": [
        415.1509409824,
        12.2064417353
      ],
      "end": [
        398.8258446587,
        12.2064417353
      ],
      "layer": "M0166-05-0001-00_DXF_FORMAT",
      "handle": "B22"
    },
    {
      "type": "LINE",
      "start": [
        272.1810579145,
        17.9873426977
      ],
      "end": [
        397.0124816079,
        17.8562700554
      ],
      "layer": "M0166-05-0001-00_DXF_FORMAT",
      "handle": "B23"
    },
    {
      "type": "LINE",
      "start": [
        90.090876414,
        297.0
      ],
      "end": [
        90.090876414,
        293.8171008285
      ],
      "layer": "M0166-05-0001-00_DXF_FORMAT",
      "handle": "B24"
    },
    {
      "type": "LINE",
      "start": [
        398.8258446587,
        28.531538059
      ],
      "end": [
        415.1509409824,
        28.531538059
      ],
      "layer": "M0166-05-0001-00_DXF_FORMAT",
      "handle": "B25"
    },
    {
      "type": "LINE",
      "start": [
        417.1768375988,
        29.8356705342
      ],
      "end": [
        272.2047675577,
        29.8265020212
      ],
      "layer": "M0166-05-0001-00_DXF_FORMAT",
      "handle": "B26"
    },
    {
      "type": "LINE",
      "start": [
        3.4048352019,
        30.0043630106
      ],
      "end": [
        0.0,
        30.0042407878
      ],
      "layer": "M0166-05-0001-00_DXF_FORMAT",
      "handle": "B27"
    },
    {
      "type": "LINE",
      "start": [
        358.5719925096,
        24.6145894429
      ],
      "end": [
        380.4125642902,
        24.4329630663
      ],
      "layer": "M0166-05-0001-00_DXF_FORMAT",
      "handle": "B28"
    },
    {
      "type": "LINE",
      "start": [
        272.3507283529,
        44.5670839903
      ],
      "end": [
        417.3287459911,
        44.3874334108
      ],
      "layer": "M0166-05-0001-00_DXF_FORMAT",
      "handle": "B29"
    },
    {
      "type": "LINE",
      "start": [
        272.2225966858,
        38.7292883456
      ],
      "end": [
        417.0365149793,
        38.4392773541
      ],
      "layer": "M0166-05-0001-00_DXF_FORMAT",
      "handle": "B2A"
    },
    {
      "type": "LINE",
      "start": [
        120.1550080799,
        297.0
      ],
      "end": [
        120.1550080799,
        293.8171008285
      ],
      "layer": "M0166-05-0001-00_DXF_FORMAT",
      "handle": "B2B"
    },
    {
      "type": "LINE",
      "start": [
        3.4037579045,
        60.0152863321
      ],
      "end": [
        -0.0,
        60.015164148
      ],
      "layer": "M0166-05-0001-00_DXF_FORMAT",
      "handle": "B2C"
    },
    {
      "type": "LINE",
      "start": [
        417.1764332906,
        56.8753834937
      ],
      "end": [
        272.2567173608,
        57.0008213372
      ],
      "layer": "M0166-05-0001-00_DXF_FORMAT",
      "handle": "B2D"
    },
    {
      "type": "LINE",
      "start": [
        272.3507283529,
        53.1903118052
      ],
      "end": [
        416.8985984351,
        52.9716242797
      ],
      "layer": "M0166-05-0001-00_DXF_FORMAT",
      "handle": "B2E"
    },
    {
      "type": "LINE",
      "start": [
        370.4231135797,
        21.4361278532
      ],
      "end": [
        360.0046733435,
        23.2979499306
      ],
      "layer": "M0166-05-0001-00_DXF_FORMAT",
      "handle": "B2F"
    },
    {
      "type": "LINE",
      "start": [
        150.1404122694,
        297.0
      ],
      "end": [
        150.1404122694,
        293.8171008285
      ],
      "layer": "M0166-05-0001-00_DXF_FORMAT",
      "handle": "B30"
    },
    {
      "type": "LINE",
      "start": [
        3.4026756245,
        90.1650104158
      ],
      "end": [
        0.0,
        90.1648882705
      ],
      "layer": "M0166-05-0001-00_DXF_FORMAT",
      "handle": "B31"
    },
    {
      "type": "LINE",
      "start": [
        180.0377057415,
        297.0
      ],
      "end": [
        180.0377057415,
        293.8171008285
      ],
      "layer": "M0166-05-0001-00_DXF_FORMAT",
      "handle": "B32"
    },
    {
      "type": "LINE",
      "start": [
        3.401601192,
        120.0961228706
      ],
      "end": [
        0.0,
        120.0960007639
      ],
      "layer": "M0166-05-0001-00_DXF_FORMAT",
      "handle": "B33"
    },
    {
      "type": "LINE",
      "start": [
        210.0,
        297.0
      ],
      "end": [
        210.0196661236,
        293.8171008285
      ],
      "layer": "M0166-05-0001-00_DXF_FORMAT",
      "handle": "B34"
    },
    {
      "type": "LINE",
      "start": [
        0.0,
        151.1157752344
      ],
      "end": [
        3.401601192,
        151.1158973412
      ],
      "layer": "M0166-05-0001-00_DXF_FORMAT",
      "handle": "B35"
    },
    {
      "type": "LINE",
      "start": [
        239.9899403675,
        297.0
      ],
      "end": [
        240.0096064911,
        293.8171008285
      ],
      "layer": "M0166-05-0001-00_DXF_FORMAT",
      "handle": "B36"
    },
    {
      "type": "LINE",
      "start": [
        3.3994409439,
        180.2754566399
      ],
      "end": [
        0.0,
        180.2753346107
      ],
      "layer": "M0166-05-0001-00_DXF_FORMAT",
      "handle": "B37"
    },
    {
      "type": "LINE",
      "start": [
        269.9673826862,
        297.0
      ],
      "end": [
        269.9870488098,
        293.8171008285
      ],
      "layer": "M0166-05-0001-00_DXF_FORMAT",
      "handle": "B38"
    },
    {
      "type": "LINE",
      "start": [
        272.2591901939,
        57.0018692156
      ],
      "end": [
        272.1449979793,
        -0.0188041688
      ],
      "layer": "M0166-05-0001-00_DXF_FORMAT",
      "handle": "B39"
    },
    {
      "type": "LINE",
      "start": [
        3.3983665122,
        210.2065462133
      ],
      "end": [
        0.0,
        210.2064242227
      ],
      "layer": "M0166-05-0001-00_DXF_FORMAT",
      "handle": "B3A"
    },
    {
      "type": "LINE",
      "start": [
        290.2322130168,
        10.7759838659
      ],
      "end": [
        290.2724219118,
        0.0
      ],
      "layer": "M0166-05-0001-00_DXF_FORMAT",
      "handle": "B3B"
    },
    {
      "type": "LINE",
      "start": [
        287.5268713184,
        56.9876039832
      ],
      "end": [
        287.5160542082,
        44.4904780196
      ],
      "layer": "M0166-05-0001-00_DXF_FORMAT",
      "handle": "B3C"
    },
    {
      "type": "LINE",
      "start": [
        300.068373953,
        297.0
      ],
      "end": [
        300.0880400766,
        293.8171008285
      ],
      "layer": "M0166-05-0001-00_DXF_FORMAT",
      "handle": "B3D"
    },
    {
      "type": "LINE",
      "start": [
        308.5368940028,
        10.7986662463
      ],
      "end": [
        308.5771875336,
        0.0
      ],
      "layer": "M0166-05-0001-00_DXF_FORMAT",
      "handle": "B3E"
    },
    {
      "type": "LINE",
      "start": [
        3.3972891972,
        240.2179615113
      ],
      "end": [
        0.0,
        240.2178395593
      ],
      "layer": "M0166-05-0001-00_DXF_FORMAT",
      "handle": "B3F"
    },
    {
      "type": "LINE",
      "start": [
        330.1392995805,
        297.0
      ],
      "end": [
        330.1589657041,
        293.8171008285
      ],
      "layer": "M0166-05-0001-00_DXF_FORMAT",
      "handle": "B40"
    },
    {
      "type": "LINE",
      "start": [
        332.3041078808,
        10.8281175647
      ],
      "end": [
        332.3175256226,
        0.0
      ],
      "layer": "M0166-05-0001-00_DXF_FORMAT",
      "handle": "B41"
    },
    {
      "type": "LINE",
      "start": [
        3.3962197388,
        270.0105060275
      ],
      "end": [
        0.0,
        270.010384114
      ],
      "layer": "M0166-05-0001-00_DXF_FORMAT",
      "handle": "B42"
    },
    {
      "type": "LINE",
      "start": [
        344.6790654852,
        0.0
      ],
      "end": [
        344.6790654852,
        10.8436368756
      ],
      "layer": "M0166-05-0001-00_DXF_FORMAT",
      "handle": "B43"
    },
    {
      "type": "LINE",
      "start": [
        344.7422409456,
        18.1766392629
      ],
      "end": [
        344.7697812902,
        44.4056094079
      ],
      "layer": "M0166-05-0001-00_DXF_FORMAT",
      "handle": "B44"
    },
    {
      "type": "LINE",
      "start": [
        40.5646638379,
        285.9011636983
      ],
      "end": [
        3.3956513522,
        285.8443955299
      ],
      "layer": "M0166-05-0001-00_DXF_FORMAT",
      "handle": "B45"
    },
    {
      "type": "LINE",
      "start": [
        40.5645571125,
        289.2087762085
      ],
      "end": [
        3.3955316739,
        289.1783453967
      ],
      "layer": "M0166-05-0001-00_DXF_FORMAT",
      "handle": "B46"
    },
    {
      "type": "LINE",
      "start": [
        40.5647705634,
        282.5935511881
      ],
      "end": [
        3.4001495399,
        282.5923520115
      ],
      "layer": "M0166-05-0001-00_DXF_FORMAT",
      "handle": "B47"
    },
    {
      "type": "LINE",
      "start": [
        0.0,
        293.8171008285
      ],
      "end": [
        420.0393322472,
        293.8171008285
      ],
      "layer": "M0166-05-0001-00_DXF_FORMAT",
      "handle": "B48"
    },
    {
      "type": "LINE",
      "start": [
        0.0,
        297.0
      ],
      "end": [
        420.0,
        297.0
      ],
      "layer": "M0166-05-0001-00_DXF_FORMAT",
      "handle": "B49"
    },
    {
      "type": "LINE",
      "start": [
        360.0323125942,
        297.0
      ],
      "end": [
        360.0323125942,
        293.8171008285
      ],
      "layer": "M0166-05-0001-00_DXF_FORMAT",
      "handle": "B4A"
    },
    {
      "type": "LINE",
      "start": [
        360.025003522,
        26.0221938612
      ],
      "end": [
        360.0046733435,
        23.2979499306
      ],
      "layer": "M0166-05-0001-00_DXF_FORMAT",
      "handle": "B4B"
    },
    {
      "type": "LINE",
      "start": [
        370.4685201739,
        27.5206114677
      ],
      "end": [
        370.4231135797,
        21.4361278532
      ],
      "layer": "M0166-05-0001-00_DXF_FORMAT",
      "handle": "B4C"
    },
    {
      "type": "LINE",
      "start": [
        376.1672605136,
        28.5245631153
      ],
      "end": [
        376.2565527627,
        19.6344127446
      ],
      "layer": "M0166-05-0001-00_DXF_FORMAT",
      "handle": "B4D"
    },
    {
      "type": "LINE",
      "start": [
        389.8971252751,
        297.0
      ],
      "end": [
        389.9167913987,
        293.8171008285
      ],
      "layer": "M0166-05-0001-00_DXF_FORMAT",
      "handle": "B4E"
    },
    {
      "type": "LINE",
      "start": [
        397.0117400696,
        29.8359679429
      ],
      "end": [
        397.0196635068,
        10.9112908276
      ],
      "layer": "M0166-05-0001-00_DXF_FORMAT",
      "handle": "B4F"
    },
    {
      "type": "LINE",
      "start": [
        398.8258446587,
        12.2064417353
      ],
      "end": [
        398.8258446587,
        28.531538059
      ],
      "layer": "M0166-05-0001-00_DXF_FORMAT",
      "handle": "B50"
    },
    {
      "type": "LINE",
      "start": [
        403.6785220923,
        10.9165616963
      ],
      "end": [
        403.6919426504,
        0.0861713145
      ],
      "layer": "M0166-05-0001-00_DXF_FORMAT",
      "handle": "B51"
    },
    {
      "type": "LINE",
      "start": [
        415.1509409824,
        28.531538059
      ],
      "end": [
        415.1509409824,
        12.2064417353
      ],
      "layer": "M0166-05-0001-00_DXF_FORMAT",
      "handle": "B52"
    },
    {
      "type": "LINE",
      "start": [
        417.1599420253,
        296.9876365599
      ],
      "end": [
        417.1787112029,
        0.2103358476
      ],
      "layer": "M0166-05-0001-00_DXF_FORMAT",
      "handle": "B53"
    },
    {
      "type": "LINE",
      "start": [
        420.0,
        0.0
      ],
      "end": [
        420.0,
        297.0
      ],
      "layer": "M0166-05-0001-00_DXF_FORMAT",
      "handle": "B54"
    },
    {
      "type": "LINE",
      "start": [
        403.5965548483,
        44.4044497567
      ],
      "end": [
        403.6120987988,
        56.9484178084
      ],
      "layer": "M0166-05-0001-00_DXF_FORMAT",
      "handle": "B55"
    },
    {
      "type": "LINE",
      "start": [
        65.5259087316,
        228.371759334
      ],
      "end": [
        65.5259087316,
        220.371759334
      ],
      "layer": "M0166-05-0001-00_DXF_DIMENSION",
      "handle": "B56"
    },
    {
      "type": "LINE",
      "start": [
        68.0287432751,
        181.7290180525
      ],
      "end": [
        68.0287432751,
        173.7290180525
      ],
      "layer": "M0166-05-0001-00_DXF_DIMENSION",
      "handle": "B57"
    },
    {
      "type": "LINE",
      "start": [
        76.3592420649,
        220.371759334
      ],
      "end": [
        76.3592420649,
        228.371759334
      ],
      "layer": "M0166-05-0001-00_DXF_DIMENSION",
      "handle": "B58"
    },
    {
      "type": "LINE",
      "start": [
        78.8620766084,
        173.7290180525
      ],
      "end": [
        78.8620766084,
        181.7290180525
      ],
      "layer": "M0166-05-0001-00_DXF_DIMENSION",
      "handle": "B59"
    },
    {
      "type": "LINE",
      "start": [
        99.9925753982,
        220.371759334
      ],
      "end": [
        99.9925753982,
        228.371759334
      ],
      "layer": "M0166-05-0001-00_DXF_DIMENSION",
      "handle": "B5A"
    },
    {
      "type": "LINE",
      "start": [
        102.4954099417,
        173.7290180525
      ],
      "end": [
        102.4954099417,
        181.7290180525
      ],
      "layer": "M0166-05-0001-00_DXF_DIMENSION",
      "handle": "B5B"
    },
    {
      "type": "LINE",
      "start": [
        106.6925753982,
        220.371759334
      ],
      "end": [
        106.6925753982,
        228.371759334
      ],
      "layer": "M0166-05-0001-00_DXF_DIMENSION",
      "handle": "B5C"
    },
    {
      "type": "LINE",
      "start": [
        109.1954099417,
        173.7290180525
      ],
      "end": [
        109.1954099417,
        181.7290180525
      ],
      "layer": "M0166-05-0001-00_DXF_DIMENSION",
      "handle": "B5D"
    },
    {
      "type": "LINE",
      "start": [
        120.2259087316,
        220.371759334
      ],
      "end": [
        120.2259087316,
        228.371759334
      ],
      "layer": "M0166-05-0001-00_DXF_DIMENSION",
      "handle": "B5E"
    },
    {
      "type": "LINE",
      "start": [
        122.7287432751,
        173.7290180525
      ],
      "end": [
        122.7287432751,
        181.7290180525
      ],
      "layer": "M0166-05-0001-00_DXF_DIMENSION",
      "handle": "B5F"
    },
    {
      "type": "LINE",
      "start": [
        133.7592420649,
        220.371759334
      ],
      "end": [
        133.7592420649,
        228.371759334
      ],
      "layer": "M0166-05-0001-00_DXF_DIMENSION",
      "handle": "B60"
    },
    {
      "type": "LINE",
      "start": [
        136.2620766084,
        173.7290180525
      ],
      "end": [
        136.2620766084,
        181.7290180525
      ],
      "layer": "M0166-05-0001-00_DXF_DIMENSION",
      "handle": "B61"
    },
    {
      "type": "LINE",
      "start": [
        142.8869250755,
        220.5596024525
      ],
      "end": [
        142.8869250755,
        160.5596024525
      ],
      "layer": "M0166-05-000DXF_CONTINUOUS_LINE",
      "handle": "B62"
    },
    {
      "type": "LINE",
      "start": [
        148.8869250755,
        154.5596024525
      ],
      "end": [
        208.8869250755,
        154.5596024525
      ],
      "layer": "M0166-05-000DXF_CONTINUOUS_LINE",
      "handle": "B63"
    },
    {
      "type": "LINE",
      "start": [
        154.8869250755,
        214.5596024525
      ],
      "end": [
        154.8869250755,
        213.4596024525
      ],
      "layer": "M0166-05-0001-00_DXF_AXIS",
      "handle": "B64"
    },
    {
      "type": "LINE",
      "start": [
        154.8869250755,
        166.5596024525
      ],
      "end": [
        154.8869250755,
        165.4596024525
      ],
      "layer": "M0166-05-0001-00_DXF_AXIS",
      "handle": "B65"
    },
    {
      "type": "LINE",
      "start": [
        154.8869250755,
        166.5596024525
      ],
      "end": [
        154.8869250755,
        167.6596024525
      ],
      "layer": "M0166-05-0001-00_DXF_AXIS",
      "handle": "B66"
    },
    {
      "type": "LINE",
      "start": [
        154.8869250755,
        214.5596024525
      ],
      "end": [
        154.8869250755,
        215.6596024525
      ],
      "layer": "M0166-05-0001-00_DXF_AXIS",
      "handle": "B67"
    },
    {
      "type": "LINE",
      "start": [
        202.8869250755,
        166.5596024525
      ],
      "end": [
        201.7869250755,
        166.5596024525
      ],
      "layer": "M0166-05-0001-00_DXF_AXIS",
      "handle": "B68"
    },
    {
      "type": "LINE",
      "start": [
        154.8869250755,
        166.5596024525
      ],
      "end": [
        153.7869250755,
        166.5596024525
      ],
      "layer": "M0166-05-0001-00_DXF_AXIS",
      "handle": "B69"
    },
    {
      "type": "LINE",
      "start": [
        154.8869250755,
        166.5596024525
      ],
      "end": [
        155.9869250755,
        166.5596024525
      ],
      "layer": "M0166-05-0001-00_DXF_AXIS",
      "handle": "B6A"
    },
    {
      "type": "LINE",
      "start": [
        202.8869250755,
        166.5596024525
      ],
      "end": [
        203.9869250755,
        166.5596024525
      ],
      "layer": "M0166-05-0001-00_DXF_AXIS",
      "handle": "B6B"
    },
    {
      "type": "LINE",
      "start": [
        68.0287432751,
        173.7290180525
      ],
      "end": [
        136.2620766084,
        173.7290180525
      ],
      "layer": "M0166-05-0001-00_DXF_DIMENSION",
      "handle": "B6C"
    },
    {
      "type": "LINE",
      "start": [
        136.2620766084,
        181.7290180525
      ],
      "end": [
        68.0287432751,
        181.7290180525
      ],
      "layer": "M0166-05-0001-00_DXF_DIMENSION",
      "handle": "B6D"
    },
    {
      "type": "LINE",
      "start": [
        173.6869250755,
        238.8839597094
      ],
      "end": [
        173.6869250755,
        246.8839597094
      ],
      "layer": "M0166-05-0001-00_DXF_DIMENSION",
      "handle": "B6E"
    },
    {
      "type": "LINE",
      "start": [
        238.9122630292,
        186.7612072865
      ],
      "end": [
        228.5122630292,
        186.7612072865
      ],
      "layer": "M0166-05-0001-00_DXF_DIMENSION",
      "handle": "B6F"
    },
    {
      "type": "LINE",
      "start": [
        178.8869250755,
        190.5596024525
      ],
      "end": [
        178.8869250755,
        168.4596024525
      ],
      "layer": "M0166-05-0001-00_DXF_AXIS",
      "handle": "B70"
    },
    {
      "type": "LINE",
      "start": [
        178.8869250755,
        190.5596024525
      ],
      "end": [
        178.8869250755,
        212.6596024525
      ],
      "layer": "M0166-05-0001-00_DXF_AXIS",
      "handle": "B71"
    },
    {
      "type": "LINE",
      "start": [
        178.8869250755,
        190.5596024525
      ],
      "end": [
        156.7869250755,
        190.5596024525
      ],
      "layer": "M0166-05-0001-00_DXF_AXIS",
      "handle": "B72"
    },
    {
      "type": "LINE",
      "start": [
        178.8869250755,
        190.5596024525
      ],
      "end": [
        200.9869250755,
        190.5596024525
      ],
      "layer": "M0166-05-0001-00_DXF_AXIS",
      "handle": "B73"
    },
    {
      "type": "LINE",
      "start": [
        184.0869250755,
        246.8839597094
      ],
      "end": [
        184.0869250755,
        238.8839597094
      ],
      "layer": "M0166-05-0001-00_DXF_DIMENSION",
      "handle": "B74"
    },
    {
      "type": "LINE",
      "start": [
        228.5122630292,
        194.7612072865
      ],
      "end": [
        238.9122630292,
        194.7612072865
      ],
      "layer": "M0166-05-0001-00_DXF_DIMENSION",
      "handle": "B75"
    },
    {
      "type": "LINE",
      "start": [
        202.8869250755,
        214.5596024525
      ],
      "end": [
        202.8869250755,
        213.4596024525
      ],
      "layer": "M0166-05-0001-00_DXF_AXIS",
      "handle": "B76"
    },
    {
      "type": "LINE",
      "start": [
        202.8869250755,
        166.5596024525
      ],
      "end": [
        202.8869250755,
        165.4596024525
      ],
      "layer": "M0166-05-0001-00_DXF_AXIS",
      "handle": "B77"
    },
    {
      "type": "LINE",
      "start": [
        202.8869250755,
        166.5596024525
      ],
      "end": [
        202.8869250755,
        167.6596024525
      ],
      "layer": "M0166-05-0001-00_DXF_AXIS",
      "handle": "B78"
    },
    {
      "type": "LINE",
      "start": [
        202.8869250755,
        214.5596024525
      ],
      "end": [
        202.8869250755,
        215.6596024525
      ],
      "layer": "M0166-05-0001-00_DXF_AXIS",
      "handle": "B79"
    },
    {
      "type": "LINE",
      "start": [
        202.8869250755,
        214.5596024525
      ],
      "end": [
        201.7869250755,
        214.5596024525
      ],
      "layer": "M0166-05-0001-00_DXF_AXIS",
      "handle": "B7A"
    },
    {
      "type": "LINE",
      "start": [
        154.8869250755,
        214.5596024525
      ],
      "end": [
        153.7869250755,
        214.5596024525
      ],
      "layer": "M0166-05-0001-00_DXF_AXIS",
      "handle": "B7B"
    },
    {
      "type": "LINE",
      "start": [
        154.8869250755,
        214.5596024525
      ],
      "end": [
        155.9869250755,
        214.5596024525
      ],
      "layer": "M0166-05-0001-00_DXF_AXIS",
      "handle": "B7C"
    },
    {
      "type": "LINE",
      "start": [
        202.8869250755,
        214.5596024525
      ],
      "end": [
        203.9869250755,
        214.5596024525
      ],
      "layer": "M0166-05-0001-00_DXF_AXIS",
      "handle": "B7D"
    },
    {
      "type": "LINE",
      "start": [
        65.5259087316,
        220.371759334
      ],
      "end": [
        133.7592420649,
        220.371759334
      ],
      "layer": "M0166-05-0001-00_DXF_DIMENSION",
      "handle": "B7E"
    },
    {
      "type": "LINE",
      "start": [
        214.8869250755,
        160.5596024525
      ],
      "end": [
        214.8869250755,
        220.5596024525
      ],
      "layer": "M0166-05-000DXF_CONTINUOUS_LINE",
      "handle": "B7F"
    },
    {
      "type": "LINE",
      "start": [
        208.8869250755,
        226.5596024525
      ],
      "end": [
        148.8869250755,
        226.5596024525
      ],
      "layer": "M0166-05-000DXF_CONTINUOUS_LINE",
      "handle": "B80"
    },
    {
      "type": "LINE",
      "start": [
        133.7592420649,
        228.371759334
      ],
      "end": [
        65.5259087316,
        228.371759334
      ],
      "layer": "M0166-05-0001-00_DXF_DIMENSION",
      "handle": "B81"
    },
    {
      "type": "LINE",
      "start": [
        228.5122630292,
        186.7612072865
      ],
      "end": [
        228.5122630292,
        194.7612072865
      ],
      "layer": "M0166-05-0001-00_DXF_DIMENSION",
      "handle": "B82"
    },
    {
      "type": "LINE",
      "start": [
        238.9122630292,
        194.7612072865
      ],
      "end": [
        238.9122630292,
        186.7612072865
      ],
      "layer": "M0166-05-0001-00_DXF_DIMENSION",
      "handle": "B83"
    },
    {
      "type": "LINE",
      "start": [
        184.0869250755,
        238.8839597094
      ],
      "end": [
        173.6869250755,
        238.8839597094
      ],
      "layer": "M0166-05-0001-00_DXF_DIMENSION",
      "handle": "B84"
    },
    {
      "type": "LINE",
      "start": [
        173.6869250755,
        246.8839597094
      ],
      "end": [
        184.0869250755,
        246.8839597094
      ],
      "layer": "M0166-05-0001-00_DXF_DIMENSION",
      "handle": "B85"
    },
    {
      "type": "LINE",
      "start": [
        117.449666168,
        257.1796033372
      ],
      "end": [
        117.449666168,
        265.1796033372
      ],
      "layer": "M0166-05-0001-00_DXF_TEXT",
      "handle": "B86"
    },
    {
      "type": "LINE",
      "start": [
        124.649666168,
        265.1796033372
      ],
      "end": [
        124.649666168,
        257.1796033372
      ],
      "layer": "M0166-05-0001-00_DXF_TEXT",
      "handle": "B87"
    },
    {
      "type": "LINE",
      "start": [
        142.8869250755,
        113.7218994646
      ],
      "end": [
        142.8869250755,
        85.7218994646
      ],
      "layer": "M0166-05-000DXF_CONTINUOUS_LINE",
      "handle": "B88"
    },
    {
      "type": "LINE",
      "start": [
        142.8869250755,
        220.5596024525
      ],
      "end": [
        142.8869250755,
        261.1796033372
      ],
      "layer": "M0166-05-0001-00_DXF_TEXT",
      "handle": "B89"
    },
    {
      "type": "LINE",
      "start": [
        148.8869250755,
        113.7218994646
      ],
      "end": [
        148.8869250755,
        85.7218994646
      ],
      "layer": "M0166-05-000DXF_CONTINUOUS_LINE",
      "handle": "B8A"
    },
    {
      "type": "LINE",
      "start": [
        150.8869250755,
        85.7218994646
      ],
      "end": [
        150.8869250755,
        113.7218994646
      ],
      "layer": "M0166-05-000DXF_CONTINUOUS_LINE",
      "handle": "B8B"
    },
    {
      "type": "LINE",
      "start": [
        154.8869250755,
        113.8218994646
      ],
      "end": [
        154.8869250755,
        85.6218994646
      ],
      "layer": "M0166-05-0001-00_DXF_AXIS",
      "handle": "B8C"
    },
    {
      "type": "LINE",
      "start": [
        156.8869250755,
        85.7218994646
      ],
      "end": [
        156.8869250755,
        113.7218994646
      ],
      "layer": "M0166-05-000DXF_CONTINUOUS_LINE",
      "handle": "B8D"
    },
    {
      "type": "LINE",
      "start": [
        158.8869250755,
        85.7218994646
      ],
      "end": [
        158.8869250755,
        113.7218994646
      ],
      "layer": "M0166-05-000DXF_CONTINUOUS_LINE",
      "handle": "B8E"
    },
    {
      "type": "LINE",
      "start": [
        163.4509428042,
        136.277727902
      ],
      "end": [
        163.4509428042,
        144.277727902
      ],
      "layer": "M0166-05-0001-00_DXF_TEXT",
      "handle": "B8F"
    },
    {
      "type": "LINE",
      "start": [
        206.8869250755,
        85.7218994646
      ],
      "end": [
        150.8869250755,
        85.7218994646
      ],
      "layer": "M0166-05-000DXF_CONTINUOUS_LINE",
      "handle": "B90"
    },
    {
      "type": "LINE",
      "start": [
        214.8869250755,
        85.7218994646
      ],
      "end": [
        142.8869250755,
        85.7218994646
      ],
      "layer": "M0166-05-000DXF_CONTINUOUS_LINE",
      "handle": "B91"
    },
    {
      "type": "LINE",
      "start": [
        167.0509428042,
        150.5596024525
      ],
      "end": [
        167.0509428042,
        144.277727902
      ],
      "layer": "M0166-05-0001-00_DXF_TEXT",
      "handle": "B92"
    },
    {
      "type": "LINE",
      "start": [
        170.6509428042,
        144.277727902
      ],
      "end": [
        170.6509428042,
        136.277727902
      ],
      "layer": "M0166-05-0001-00_DXF_TEXT",
      "handle": "B93"
    },
    {
      "type": "LINE",
      "start": [
        178.8869250755,
        113.8218994646
      ],
      "end": [
        178.8869250755,
        85.6218994646
      ],
      "layer": "M0166-05-0001-00_DXF_AXIS",
      "handle": "B94"
    },
    {
      "type": "LINE",
      "start": [
        231.5662384726,
        97.9512301788
      ],
      "end": [
        224.3662384726,
        97.9512301788
      ],
      "layer": "M0166-05-0001-00_DXF_TEXT",
      "handle": "B95"
    },
    {
      "type": "LINE",
      "start": [
        218.8869250755,
        101.9512301788
      ],
      "end": [
        224.3662384726,
        101.9512301788
      ],
      "layer": "M0166-05-0001-00_DXF_TEXT",
      "handle": "B96"
    },
    {
      "type": "LINE",
      "start": [
        224.3662384726,
        105.9512301788
      ],
      "end": [
        231.5662384726,
        105.9512301788
      ],
      "layer": "M0166-05-0001-00_DXF_TEXT",
      "handle": "B97"
    },
    {
      "type": "LINE",
      "start": [
        206.8869250755,
        113.7218994646
      ],
      "end": [
        150.8869250755,
        113.7218994646
      ],
      "layer": "M0166-05-000DXF_CONTINUOUS_LINE",
      "handle": "B98"
    },
    {
      "type": "LINE",
      "start": [
        214.8869250755,
        113.7218994646
      ],
      "end": [
        142.8869250755,
        113.7218994646
      ],
      "layer": "M0166-05-000DXF_CONTINUOUS_LINE",
      "handle": "B99"
    },
    {
      "type": "LINE",
      "start": [
        198.8869250755,
        85.7218994646
      ],
      "end": [
        198.8869250755,
        113.7218994646
      ],
      "layer": "M0166-05-000DXF_CONTINUOUS_LINE",
      "handle": "B9A"
    },
    {
      "type": "LINE",
      "start": [
        200.8869250755,
        85.7218994646
      ],
      "end": [
        200.8869250755,
        113.7218994646
      ],
      "layer": "M0166-05-000DXF_CONTINUOUS_LINE",
      "handle": "B9B"
    },
    {
      "type": "LINE",
      "start": [
        202.8869250755,
        113.8218994646
      ],
      "end": [
        202.8869250755,
        85.6218994646
      ],
      "layer": "M0166-05-0001-00_DXF_AXIS",
      "handle": "B9C"
    },
    {
      "type": "LINE",
      "start": [
        206.8869250755,
        85.7218994646
      ],
      "end": [
        206.8869250755,
        113.7218994646
      ],
      "layer": "M0166-05-000DXF_CONTINUOUS_LINE",
      "handle": "B9D"
    },
    {
      "type": "LINE",
      "start": [
        208.8869250755,
        113.7218994646
      ],
      "end": [
        208.8869250755,
        85.7218994646
      ],
      "layer": "M0166-05-000DXF_CONTINUOUS_LINE",
      "handle": "B9E"
    },
    {
      "type": "LINE",
      "start": [
        214.8869250755,
        113.7218994646
      ],
      "end": [
        214.8869250755,
        85.7218994646
      ],
      "layer": "M0166-05-000DXF_CONTINUOUS_LINE",
      "handle": "B9F"
    },
    {
      "type": "LINE",
      "start": [
        224.3662384726,
        97.9512301788
      ],
      "end": [
        224.3662384726,
        105.9512301788
      ],
      "layer": "M0166-05-0001-00_DXF_TEXT",
      "handle": "BA0"
    },
    {
      "type": "LINE",
      "start": [
        231.5662384726,
        105.9512301788
      ],
      "end": [
        231.5662384726,
        97.9512301788
      ],
      "layer": "M0166-05-0001-00_DXF_TEXT",
      "handle": "BA1"
    },
    {
      "type": "LINE",
      "start": [
        170.6509428042,
        136.277727902
      ],
      "end": [
        163.4509428042,
        136.277727902
      ],
      "layer": "M0166-05-0001-00_DXF_TEXT",
      "handle": "BA2"
    },
    {
      "type": "LINE",
      "start": [
        163.4509428042,
        144.277727902
      ],
      "end": [
        170.6509428042,
        144.277727902
      ],
      "layer": "M0166-05-0001-00_DXF_TEXT",
      "handle": "BA3"
    },
    {
      "type": "LINE",
      "start": [
        124.649666168,
        257.1796033372
      ],
      "end": [
        117.449666168,
        257.1796033372
      ],
      "layer": "M0166-05-0001-00_DXF_TEXT",
      "handle": "BA4"
    },
    {
      "type": "LINE",
      "start": [
        138.8869250755,
        261.1796033372
      ],
      "end": [
        124.649666168,
        261.1796033372
      ],
      "layer": "M0166-05-0001-00_DXF_TEXT",
      "handle": "BA5"
    },
    {
      "type": "LINE",
      "start": [
        117.449666168,
        265.1796033372
      ],
      "end": [
        124.649666168,
        265.1796033372
      ],
      "layer": "M0166-05-0001-00_DXF_TEXT",
      "handle": "BA6"
    }
  ],
  "arrow_associations": [
    {
      "arrow": {
        "type": "LINE",
        "start": [
          133.7592420649,
          220.371759334
        ],
        "end": [
          133.7592420649,
          228.371759334
        ],
        "layer": "M0166-05-0001-00_DXF_DIMENSION",
        "handle": "B60"
      },
      "dimension": {
        "type": "DIMENSION",
        "dimension_type": null,
        "text": "FLANGE MODEL TARGET",
        "measured": null,
        "pos": [
          151.2107776952,
          216.1362889902
        ],
        "layer": "M0166-05-0001-00_DXF_DIMENSION",
        "handle": "B0A",
        "Z": false,
        "text_ai": "SIZE\nA3",
        "text_ai_source": "SCALE\nDESIGNATION\nSIZE\nA3"
      },
      "distance": 17.95815427288782
    },
    {
      "arrow": {
        "type": "LINE",
        "start": [
          136.2620766084,
          173.7290180525
        ],
        "end": [
          136.2620766084,
          181.7290180525
        ],
        "layer": "M0166-05-0001-00_DXF_DIMENSION",
        "handle": "B61"
      },
      "dimension": {
        "type": "DIMENSION",
        "dimension_type": null,
        "text": "4x R6",
        "measured": null,
        "pos": [
          148.8869250755,
          160.5596024525
        ],
        "layer": "M0166-05-0001-00_DXF_DIMENSION",
        "handle": "B0D",
        "Z": false,
        "text_ai": "4 x R6",
        "text_ai_source": "4x R6"
      },
      "distance": 18.243363342946395
    },
    {
      "arrow": {
        "type": "LINE",
        "start": [
          154.8869250755,
          166.5596024525
        ],
        "end": [
          154.8869250755,
          165.4596024525
        ],
        "layer": "M0166-05-0001-00_DXF_AXIS",
        "handle": "B65"
      },
      "dimension": {
        "type": "DIMENSION",
        "dimension_type": null,
        "text": "M0166-05-0001-00",
        "measured": null,
        "pos": [
          157.7526338486,
          184.4488140963
        ],
        "layer": "M0166-05-0001-00_DXF_DIMENSION",
        "handle": "AF9",
        "Z": false,
        "text_ai": "M0166-05-0001-00",
        "text_ai_source": "M0166-05-0001-00"
      },
      "distance": 18.117289532623023
    },
    {
      "arrow": {
        "type": "LINE",
        "start": [
          184.0869250755,
          246.8839597094
        ],
        "end": [
          184.0869250755,
          238.8839597094
        ],
        "layer": "M0166-05-0001-00_DXF_DIMENSION",
        "handle": "B74"
      },
      "dimension": {
        "type": "DIMENSION",
        "dimension_type": null,
        "text": "48",
        "measured": null,
        "pos": [
          202.8869250755,
          242.8839597094
        ],
        "layer": "M0166-05-0001-00_DXF_DIMENSION",
        "handle": "B0B",
        "Z": false,
        "text_ai": "48",
        "text_ai_source": "48"
      },
      "distance": 19.220822042774323
    },
    {
      "arrow": {
        "type": "LINE",
        "start": [
          142.8869250755,
          113.7218994646
        ],
        "end": [
          142.8869250755,
          85.7218994646
        ],
        "layer": "M0166-05-000DXF_CONTINUOUS_LINE",
        "handle": "B88"
      },
      "dimension": {
        "type": "DIMENSION",
        "dimension_type": null,
        "text": "28",
        "measured": null,
        "pos": [
          131.9992165024,
          113.7218994646
        ],
        "layer": "M0166-05-0001-00_DXF_DIMENSION",
        "handle": "AE6",
        "Z": false,
        "text_ai": "28",
        "text_ai_source": "28"
      },
      "distance": 10.887708573099985
    }
  ],
  "arrows_orphans": [],
  "audit": {
    "datums_found": 10,
    "dimensions_found": 8,
    "arrows_found": 163,
    "arrows_associated": 5,
    "arrows_orphans": 158,
    "audit_time": "2025-06-09 18:01:07 UTC"
  },
  "info": {
    "module": "Module C DXF Extraction Noyau Mtier (Fusion v3 + OCR + PDF vectoriel + AI Ollama)",
    "version": "2025-06-09",
    "datetime": "2025-06-09 18:01:07 UTC",
    "input_dxf": "F:/MetricX_beta_0.1/CAD_datas/M0166-05-0001-00/m0166-05-0001-00.dxf"
  }
}